{"namespace":"GordaDesignSystem_019e24","components":[{"name":"Avatar","sourcePath":"components/data/Avatar.jsx"},{"name":"Card","sourcePath":"components/data/Card.jsx"},{"name":"StatCard","sourcePath":"components/data/StatCard.jsx"},{"name":"Alert","sourcePath":"components/feedback/Alert.jsx"},{"name":"Badge","sourcePath":"components/feedback/Badge.jsx"},{"name":"StatusBadge","sourcePath":"components/feedback/StatusBadge.jsx"},{"name":"Button","sourcePath":"components/forms/Button.jsx"},{"name":"Input","sourcePath":"components/forms/Input.jsx"},{"name":"Select","sourcePath":"components/forms/Select.jsx"},{"name":"Switch","sourcePath":"components/forms/Switch.jsx"}],"startingPoints":[{"name":"admin","path":"ui_kits/admin/index.html","previewPath":"ui_kits/admin/index.html","kind":"screen","section":"Admin","subtitle":"Full Gorda admin dashboard shell","viewport":"1280x800"}],"cards":[{"path":"ui_kits/admin/index.html","group":"Admin","viewport":"1280x800","subtitle":"Login → dashboard, services, drivers & settings","name":"Gorda Admin — full app"},{"path":"cards/brand-iconography.html","group":"Brand","viewport":"700x180","subtitle":"Font Awesome 6 solid/brands · white icon-chip pattern","name":"Iconography"},{"path":"cards/brand-logo.html","group":"Brand","viewport":"700x180","subtitle":"Gorda mark — the magenta cat, rounded-lg on light & dark","name":"Logo"},{"path":"cards/color-brand.html","group":"Colors","viewport":"700x150","subtitle":"Gorda magenta — primary actions & active state","name":"Brand · Primary"},{"path":"cards/color-dark.html","group":"Colors","viewport":"700x220","subtitle":"Surface, text & border tokens for [data-theme=dark]","name":"Dark theme"},{"path":"cards/color-domain.html","group":"Colors","viewport":"700x150","subtitle":"WhatsApp green, driver amber & service status colors","name":"Domain accents"},{"path":"cards/color-gradients.html","group":"Colors","viewport":"700x150","subtitle":"Signature Soft UI 310° gradients for fills & accents","name":"Gradients"},{"path":"cards/color-neutral.html","group":"Colors","viewport":"700x130","subtitle":"Gray scale — backgrounds, borders, muted text","name":"Neutral ramp"},{"path":"cards/color-semantic.html","group":"Colors","viewport":"700x150","subtitle":"Status & intent colors — info, success, warning, danger, secondary","name":"Semantic"},{"path":"components/data/data.card.html","group":"Components","viewport":"700x260","subtitle":"Surface card, KPI stat tiles & avatars","name":"Cards, Stats & Avatars"},{"path":"components/feedback/feedback.card.html","group":"Components","viewport":"700x220","subtitle":"Status badges, soft/solid badges & gradient alerts","name":"Badges & Alerts"},{"path":"components/forms/forms.card.html","group":"Components","viewport":"700x300","subtitle":"Buttons, inputs, select & switch","name":"Buttons & Forms"},{"path":"cards/spacing-radii.html","group":"Spacing","viewport":"700x160","subtitle":"Corner radii — md inputs/buttons, xl cards, pill badges","name":"Radii"},{"path":"cards/spacing-scale.html","group":"Spacing","viewport":"700x160","subtitle":"Bootstrap spacers · 4 / 8 / 16 / 24 / 48 / 64 px","name":"Spacing scale"},{"path":"cards/spacing-shadows.html","group":"Spacing","viewport":"700x180","subtitle":"Elevation — xs, sm, card (signature), lg, button","name":"Shadows"},{"path":"cards/type-body.html","group":"Type","viewport":"700x280","subtitle":"Body, lead, small, captions & table-head eyebrow","name":"Body & utility text"},{"path":"cards/type-headings.html","group":"Type","viewport":"700x320","subtitle":"Open Sans 700 · h1–h6 with px sizes","name":"Heading scale"},{"path":"cards/type-weights.html","group":"Type","viewport":"700x150","subtitle":"Open Sans · 300 / 400 / 600 / 700","name":"Weights & font"}],"templates":[],"hasThumbnailHtml":false,"globalCssPaths":["tokens/fonts.css","tokens/colors.css","tokens/typography.css","tokens/spacing.css","tokens/base.css","styles.css"],"tokens":[{"name":"--gray-100","value":"#f8f9fa","kind":"color","definedIn":"tokens/colors.css"},{"name":"--gray-200","value":"#e9ecef","kind":"color","definedIn":"tokens/colors.css"},{"name":"--gray-300","value":"#dee2e6","kind":"color","definedIn":"tokens/colors.css"},{"name":"--gray-400","value":"#ced4da","kind":"color","definedIn":"tokens/colors.css"},{"name":"--gray-500","value":"#adb5bd","kind":"color","definedIn":"tokens/colors.css"},{"name":"--gray-600","value":"#6c757d","kind":"color","definedIn":"tokens/colors.css"},{"name":"--gray-700","value":"#495057","kind":"color","definedIn":"tokens/colors.css"},{"name":"--gray-800","value":"#343a40","kind":"color","definedIn":"tokens/colors.css"},{"name":"--gray-900","value":"#212529","kind":"color","definedIn":"tokens/colors.css"},{"name":"--white","value":"#ffffff","kind":"color","definedIn":"tokens/colors.css"},{"name":"--black","value":"#000000","kind":"color","definedIn":"tokens/colors.css"},{"name":"--primary","value":"#cb0c9f","kind":"color","definedIn":"tokens/colors.css"},{"name":"--secondary","value":"#8392ab","kind":"color","definedIn":"tokens/colors.css"},{"name":"--info","value":"#17c1e8","kind":"color","definedIn":"tokens/colors.css"},{"name":"--success","value":"#82d616","kind":"color","definedIn":"tokens/colors.css"},{"name":"--warning","value":"#fbcf33","kind":"color","definedIn":"tokens/colors.css"},{"name":"--danger","value":"#ea0606","kind":"color","definedIn":"tokens/colors.css"},{"name":"--light","value":"#252d3d","kind":"color","definedIn":"tokens/colors.css"},{"name":"--dark","value":"#e0e7f0","kind":"color","definedIn":"tokens/colors.css"},{"name":"--text-heading","value":"#ffffff","kind":"font","definedIn":"tokens/colors.css"},{"name":"--text-body","value":"#a8b8d8","kind":"font","definedIn":"tokens/colors.css"},{"name":"--text-muted","value":"#7b88a8","kind":"font","definedIn":"tokens/colors.css"},{"name":"--text-secondary","value":"#8392ab","kind":"font","definedIn":"tokens/colors.css"},{"name":"--body-bg","value":"#1a1f2e","kind":"color","definedIn":"tokens/colors.css"},{"name":"--surface-card","value":"#252d3d","kind":"color","definedIn":"tokens/colors.css"},{"name":"--surface-input","value":"#1e2536","kind":"color","definedIn":"tokens/colors.css"},{"name":"--border-color","value":"#344767","kind":"color","definedIn":"tokens/colors.css"},{"name":"--border-subtle","value":"#2d3655","kind":"color","definedIn":"tokens/colors.css"},{"name":"--gradient-primary","value":"linear-gradient(310deg, #7928ca, #ff0080)","kind":"color","definedIn":"tokens/colors.css","annotation":"color"},{"name":"--gradient-secondary","value":"linear-gradient(310deg, #627594, #a8b8d8)","kind":"color","definedIn":"tokens/colors.css","annotation":"color"},{"name":"--gradient-info","value":"linear-gradient(310deg, #2152ff, #21d4fd)","kind":"color","definedIn":"tokens/colors.css","annotation":"color"},{"name":"--gradient-success","value":"linear-gradient(310deg, #17ad37, #98ec2d)","kind":"color","definedIn":"tokens/colors.css","annotation":"color"},{"name":"--gradient-warning","value":"linear-gradient(310deg, #f53939, #fbcf33)","kind":"color","definedIn":"tokens/colors.css","annotation":"color"},{"name":"--gradient-danger","value":"linear-gradient(310deg, #d60808, #ff6690)","kind":"color","definedIn":"tokens/colors.css","annotation":"color"},{"name":"--gradient-dark","value":"linear-gradient(310deg, #141727, #3a416f)","kind":"color","definedIn":"tokens/colors.css","annotation":"color"},{"name":"--gradient-light","value":"linear-gradient(310deg, #ced4da, #ebeff4)","kind":"color","definedIn":"tokens/colors.css","annotation":"color"},{"name":"--text-gradient-info","value":"linear-gradient(310deg, #2152ff, #21d4fd)","kind":"color","definedIn":"tokens/colors.css","annotation":"color"},{"name":"--text-gradient-primary","value":"linear-gradient(310deg, #7928ca, #ff0080)","kind":"color","definedIn":"tokens/colors.css","annotation":"color"},{"name":"--whatsapp-green","value":"#25d366","kind":"color","definedIn":"tokens/colors.css"},{"name":"--whatsapp-header","value":"#075e54","kind":"color","definedIn":"tokens/colors.css"},{"name":"--whatsapp-chat-bg","value":"#e5ddd5","kind":"color","definedIn":"tokens/colors.css"},{"name":"--driver-amber","value":"#fbbf24","kind":"color","definedIn":"tokens/colors.css"},{"name":"--driver-amber-text","value":"#b45309","kind":"font","definedIn":"tokens/colors.css"},{"name":"--status-pending","value":"#fbcf33","kind":"color","definedIn":"tokens/colors.css"},{"name":"--status-in-progress","value":"#17c1e8","kind":"color","definedIn":"tokens/colors.css"},{"name":"--status-completed","value":"#82d616","kind":"color","definedIn":"tokens/colors.css"},{"name":"--status-canceled","value":"#ea0606","kind":"color","definedIn":"tokens/colors.css"},{"name":"--badge-primary-bg","value":"#3a0826","kind":"color","definedIn":"tokens/colors.css"},{"name":"--badge-primary-fg","value":"#f296db","kind":"color","definedIn":"tokens/colors.css"},{"name":"--badge-secondary-bg","value":"#1e263a","kind":"color","definedIn":"tokens/colors.css"},{"name":"--badge-secondary-fg","value":"#8fa9cc","kind":"color","definedIn":"tokens/colors.css"},{"name":"--badge-info-bg","value":"#0b1d40","kind":"color","definedIn":"tokens/colors.css"},{"name":"--badge-info-fg","value":"#4ec9f5","kind":"color","definedIn":"tokens/colors.css"},{"name":"--badge-success-bg","value":"#0e2b06","kind":"color","definedIn":"tokens/colors.css"},{"name":"--badge-success-fg","value":"#aad94b","kind":"color","definedIn":"tokens/colors.css"},{"name":"--badge-warning-bg","value":"#2c1f00","kind":"color","definedIn":"tokens/colors.css"},{"name":"--badge-warning-fg","value":"#f7d354","kind":"color","definedIn":"tokens/colors.css"},{"name":"--badge-danger-bg","value":"#2c0606","kind":"color","definedIn":"tokens/colors.css"},{"name":"--badge-danger-fg","value":"#f56666","kind":"color","definedIn":"tokens/colors.css"},{"name":"--badge-dark-bg","value":"#1a1f2e","kind":"color","definedIn":"tokens/colors.css"},{"name":"--badge-dark-fg","value":"#a8b8d8","kind":"color","definedIn":"tokens/colors.css"},{"name":"--badge-light-bg","value":"#252d3d","kind":"color","definedIn":"tokens/colors.css"},{"name":"--badge-light-fg","value":"#8392ab","kind":"color","definedIn":"tokens/colors.css"},{"name":"--surface-disabled","value":"#1a1f2e","kind":"color","definedIn":"tokens/colors.css"},{"name":"--body-bg","value":"#1a1f2e","kind":"color","definedIn":"tokens/colors.css","scope":"[data-theme=\"dark\"]"},{"name":"--surface-card","value":"#252d3d","kind":"color","definedIn":"tokens/colors.css","scope":"[data-theme=\"dark\"]"},{"name":"--surface-input","value":"#1e2536","kind":"color","definedIn":"tokens/colors.css","scope":"[data-theme=\"dark\"]"},{"name":"--surface-disabled","value":"#1a1f2e","kind":"color","definedIn":"tokens/colors.css","scope":"[data-theme=\"dark\"]"},{"name":"--text-heading","value":"#ffffff","kind":"font","definedIn":"tokens/colors.css","scope":"[data-theme=\"dark\"]"},{"name":"--text-body","value":"#a8b8d8","kind":"font","definedIn":"tokens/colors.css","scope":"[data-theme=\"dark\"]"},{"name":"--text-muted","value":"#7b88a8","kind":"font","definedIn":"tokens/colors.css","scope":"[data-theme=\"dark\"]"},{"name":"--text-secondary","value":"#8392ab","kind":"font","definedIn":"tokens/colors.css","scope":"[data-theme=\"dark\"]"},{"name":"--border-color","value":"#344767","kind":"color","definedIn":"tokens/colors.css","scope":"[data-theme=\"dark\"]"},{"name":"--border-subtle","value":"#2d3655","kind":"color","definedIn":"tokens/colors.css","scope":"[data-theme=\"dark\"]"},{"name":"--light","value":"#252d3d","kind":"color","definedIn":"tokens/colors.css","scope":"[data-theme=\"dark\"]"},{"name":"--dark","value":"#e0e7f0","kind":"color","definedIn":"tokens/colors.css","scope":"[data-theme=\"dark\"]"},{"name":"--shadow-card","value":"0 20px 27px 0 rgba(0, 0, 0, 0.4)","kind":"shadow","definedIn":"tokens/colors.css","scope":"[data-theme=\"dark\"]"},{"name":"--shadow-blur","value":"inset 0 0 1px 1px rgba(255, 255, 255, 0.06), 0 20px 27px 0 rgba(0, 0, 0, 0.4)","kind":"shadow","definedIn":"tokens/colors.css","scope":"[data-theme=\"dark\"]"},{"name":"--shadow-sm","value":"0 0.25rem 0.375rem -0.0625rem rgba(0, 0, 0, 0.3), 0 0.125rem 0.25rem -0.0625rem rgba(0, 0, 0, 0.2)","kind":"shadow","definedIn":"tokens/colors.css","scope":"[data-theme=\"dark\"]"},{"name":"--badge-primary-bg","value":"#3a0826","kind":"color","definedIn":"tokens/colors.css","scope":"[data-theme=\"dark\"]"},{"name":"--badge-primary-fg","value":"#f296db","kind":"color","definedIn":"tokens/colors.css","scope":"[data-theme=\"dark\"]"},{"name":"--badge-secondary-bg","value":"#1e263a","kind":"color","definedIn":"tokens/colors.css","scope":"[data-theme=\"dark\"]"},{"name":"--badge-secondary-fg","value":"#8fa9cc","kind":"color","definedIn":"tokens/colors.css","scope":"[data-theme=\"dark\"]"},{"name":"--badge-info-bg","value":"#0b1d40","kind":"color","definedIn":"tokens/colors.css","scope":"[data-theme=\"dark\"]"},{"name":"--badge-info-fg","value":"#4ec9f5","kind":"color","definedIn":"tokens/colors.css","scope":"[data-theme=\"dark\"]"},{"name":"--badge-success-bg","value":"#0e2b06","kind":"color","definedIn":"tokens/colors.css","scope":"[data-theme=\"dark\"]"},{"name":"--badge-success-fg","value":"#aad94b","kind":"color","definedIn":"tokens/colors.css","scope":"[data-theme=\"dark\"]"},{"name":"--badge-warning-bg","value":"#2c1f00","kind":"color","definedIn":"tokens/colors.css","scope":"[data-theme=\"dark\"]"},{"name":"--badge-warning-fg","value":"#f7d354","kind":"color","definedIn":"tokens/colors.css","scope":"[data-theme=\"dark\"]"},{"name":"--badge-danger-bg","value":"#2c0606","kind":"color","definedIn":"tokens/colors.css","scope":"[data-theme=\"dark\"]"},{"name":"--badge-danger-fg","value":"#f56666","kind":"color","definedIn":"tokens/colors.css","scope":"[data-theme=\"dark\"]"},{"name":"--badge-dark-bg","value":"#1a1f2e","kind":"color","definedIn":"tokens/colors.css","scope":"[data-theme=\"dark\"]"},{"name":"--badge-dark-fg","value":"#a8b8d8","kind":"color","definedIn":"tokens/colors.css","scope":"[data-theme=\"dark\"]"},{"name":"--badge-light-bg","value":"#252d3d","kind":"color","definedIn":"tokens/colors.css","scope":"[data-theme=\"dark\"]"},{"name":"--badge-light-fg","value":"#8392ab","kind":"color","definedIn":"tokens/colors.css","scope":"[data-theme=\"dark\"]"},{"name":"--shadow-card","value":"0 20px 27px 0 rgba(0, 0, 0, 0.05)","kind":"shadow","definedIn":"tokens/spacing.css"},{"name":"--shadow-blur","value":"inset 0 0 1px 1px rgba(255, 255, 255, 0.9), 0 20px 27px 0 rgba(0, 0, 0, 0.05)","kind":"shadow","definedIn":"tokens/spacing.css"},{"name":"--shadow-sm","value":"0 0.25rem 0.375rem -0.0625rem rgba(20, 20, 20, 0.12), 0 0.125rem 0.25rem -0.0625rem rgba(20, 20, 20, 0.07)","kind":"shadow","definedIn":"tokens/spacing.css"},{"name":"--body-bg","value":"#f8f9fa","kind":"color","definedIn":"tokens/colors.css","scope":"[data-theme=\"light\"]"},{"name":"--surface-card","value":"#ffffff","kind":"color","definedIn":"tokens/colors.css","scope":"[data-theme=\"light\"]"},{"name":"--surface-input","value":"#ffffff","kind":"color","definedIn":"tokens/colors.css","scope":"[data-theme=\"light\"]"},{"name":"--surface-disabled","value":"#e9ecef","kind":"color","definedIn":"tokens/colors.css","scope":"[data-theme=\"light\"]"},{"name":"--text-heading","value":"#344767","kind":"font","definedIn":"tokens/colors.css","scope":"[data-theme=\"light\"]"},{"name":"--text-body","value":"#67748e","kind":"font","definedIn":"tokens/colors.css","scope":"[data-theme=\"light\"]"},{"name":"--text-muted","value":"#6c757d","kind":"font","definedIn":"tokens/colors.css","scope":"[data-theme=\"light\"]"},{"name":"--text-secondary","value":"#8392ab","kind":"font","definedIn":"tokens/colors.css","scope":"[data-theme=\"light\"]"},{"name":"--border-color","value":"#d2d6da","kind":"color","definedIn":"tokens/colors.css","scope":"[data-theme=\"light\"]"},{"name":"--border-subtle","value":"#dee2e6","kind":"color","definedIn":"tokens/colors.css","scope":"[data-theme=\"light\"]"},{"name":"--light","value":"#e9ecef","kind":"color","definedIn":"tokens/colors.css","scope":"[data-theme=\"light\"]"},{"name":"--dark","value":"#344767","kind":"color","definedIn":"tokens/colors.css","scope":"[data-theme=\"light\"]"},{"name":"--shadow-card","value":"0 20px 27px 0 rgba(0, 0, 0, 0.05)","kind":"shadow","definedIn":"tokens/colors.css","scope":"[data-theme=\"light\"]"},{"name":"--shadow-blur","value":"inset 0 0 1px 1px rgba(255, 255, 255, 0.9), 0 20px 27px 0 rgba(0, 0, 0, 0.05)","kind":"shadow","definedIn":"tokens/colors.css","scope":"[data-theme=\"light\"]"},{"name":"--shadow-sm","value":"0 0.25rem 0.375rem -0.0625rem rgba(20, 20, 20, 0.12), 0 0.125rem 0.25rem -0.0625rem rgba(20, 20, 20, 0.07)","kind":"shadow","definedIn":"tokens/colors.css","scope":"[data-theme=\"light\"]"},{"name":"--badge-primary-bg","value":"#fde6f7","kind":"color","definedIn":"tokens/colors.css","scope":"[data-theme=\"light\"]"},{"name":"--badge-primary-fg","value":"#a30c80","kind":"color","definedIn":"tokens/colors.css","scope":"[data-theme=\"light\"]"},{"name":"--badge-secondary-bg","value":"#eef1f6","kind":"color","definedIn":"tokens/colors.css","scope":"[data-theme=\"light\"]"},{"name":"--badge-secondary-fg","value":"#5b6b8c","kind":"color","definedIn":"tokens/colors.css","scope":"[data-theme=\"light\"]"},{"name":"--badge-info-bg","value":"#dcf6fd","kind":"color","definedIn":"tokens/colors.css","scope":"[data-theme=\"light\"]"},{"name":"--badge-info-fg","value":"#0a7c97","kind":"color","definedIn":"tokens/colors.css","scope":"[data-theme=\"light\"]"},{"name":"--badge-success-bg","value":"#eafad0","kind":"color","definedIn":"tokens/colors.css","scope":"[data-theme=\"light\"]"},{"name":"--badge-success-fg","value":"#4d8b00","kind":"color","definedIn":"tokens/colors.css","scope":"[data-theme=\"light\"]"},{"name":"--badge-warning-bg","value":"#fef6d8","kind":"color","definedIn":"tokens/colors.css","scope":"[data-theme=\"light\"]"},{"name":"--badge-warning-fg","value":"#9a7b00","kind":"color","definedIn":"tokens/colors.css","scope":"[data-theme=\"light\"]"},{"name":"--badge-danger-bg","value":"#fde0e0","kind":"color","definedIn":"tokens/colors.css","scope":"[data-theme=\"light\"]"},{"name":"--badge-danger-fg","value":"#b30505","kind":"color","definedIn":"tokens/colors.css","scope":"[data-theme=\"light\"]"},{"name":"--badge-dark-bg","value":"#e3e7ef","kind":"color","definedIn":"tokens/colors.css","scope":"[data-theme=\"light\"]"},{"name":"--badge-dark-fg","value":"#344767","kind":"color","definedIn":"tokens/colors.css","scope":"[data-theme=\"light\"]"},{"name":"--badge-light-bg","value":"#f4f6f9","kind":"color","definedIn":"tokens/colors.css","scope":"[data-theme=\"light\"]"},{"name":"--badge-light-fg","value":"#67748e","kind":"color","definedIn":"tokens/colors.css","scope":"[data-theme=\"light\"]"},{"name":"--font-sans","value":"'Open Sans', -apple-system, BlinkMacSystemFont, 'Segoe UI', Roboto, sans-serif","kind":"font","definedIn":"tokens/typography.css"},{"name":"--font-mono","value":"'SFMono-Regular', Menlo, Monaco, Consolas, 'Liberation Mono', 'Courier New', monospace","kind":"font","definedIn":"tokens/typography.css"},{"name":"--fw-light","value":"300","kind":"font","definedIn":"tokens/typography.css","annotation":"font"},{"name":"--fw-normal","value":"400","kind":"font","definedIn":"tokens/typography.css","annotation":"font"},{"name":"--fw-bold","value":"600","kind":"font","definedIn":"tokens/typography.css","annotation":"font"},{"name":"--fw-bolder","value":"700","kind":"font","definedIn":"tokens/typography.css","annotation":"font"},{"name":"--fs-root","value":"16px","kind":"spacing","definedIn":"tokens/typography.css"},{"name":"--fs-body","value":"1rem","kind":"spacing","definedIn":"tokens/typography.css"},{"name":"--fs-h1","value":"3rem","kind":"spacing","definedIn":"tokens/typography.css"},{"name":"--fs-h2","value":"2.25rem","kind":"spacing","definedIn":"tokens/typography.css"},{"name":"--fs-h3","value":"1.875rem","kind":"spacing","definedIn":"tokens/typography.css"},{"name":"--fs-h4","value":"1.5rem","kind":"spacing","definedIn":"tokens/typography.css"},{"name":"--fs-h5","value":"1.25rem","kind":"spacing","definedIn":"tokens/typography.css"},{"name":"--fs-h6","value":"1rem","kind":"spacing","definedIn":"tokens/typography.css"},{"name":"--fs-lead","value":"1.25rem","kind":"spacing","definedIn":"tokens/typography.css"},{"name":"--fs-lg","value":"1.125rem","kind":"spacing","definedIn":"tokens/typography.css"},{"name":"--fs-sm","value":"0.875rem","kind":"spacing","definedIn":"tokens/typography.css"},{"name":"--fs-xs","value":"0.75rem","kind":"spacing","definedIn":"tokens/typography.css"},{"name":"--fs-xxs","value":"0.65rem","kind":"spacing","definedIn":"tokens/typography.css"},{"name":"--lh-tight","value":"1.2","kind":"font","definedIn":"tokens/typography.css","annotation":"font"},{"name":"--lh-base","value":"1.6","kind":"font","definedIn":"tokens/typography.css","annotation":"font"},{"name":"--lh-snug","value":"1.375","kind":"font","definedIn":"tokens/typography.css","annotation":"font"},{"name":"--ls-tighter","value":"-0.05rem","kind":"font","definedIn":"tokens/typography.css","annotation":"font"},{"name":"--ls-tight","value":"-0.025rem","kind":"font","definedIn":"tokens/typography.css","annotation":"font"},{"name":"--ls-normal","value":"0","kind":"font","definedIn":"tokens/typography.css","annotation":"font"},{"name":"--ls-wide","value":"0.05rem","kind":"font","definedIn":"tokens/typography.css","annotation":"font"},{"name":"--heading-weight","value":"700","kind":"font","definedIn":"tokens/typography.css","annotation":"font"},{"name":"--heading-color","value":"var(--text-heading)","kind":"color","definedIn":"tokens/typography.css","annotation":"color"},{"name":"--space-0","value":"0","kind":"spacing","definedIn":"tokens/spacing.css"},{"name":"--space-1","value":"0.25rem","kind":"spacing","definedIn":"tokens/spacing.css"},{"name":"--space-2","value":"0.5rem","kind":"spacing","definedIn":"tokens/spacing.css"},{"name":"--space-3","value":"1rem","kind":"spacing","definedIn":"tokens/spacing.css"},{"name":"--space-4","value":"1.5rem","kind":"spacing","definedIn":"tokens/spacing.css"},{"name":"--space-5","value":"3rem","kind":"spacing","definedIn":"tokens/spacing.css"},{"name":"--space-6","value":"4rem","kind":"spacing","definedIn":"tokens/spacing.css"},{"name":"--space-7","value":"6rem","kind":"spacing","definedIn":"tokens/spacing.css"},{"name":"--radius-xs","value":"0.125rem","kind":"radius","definedIn":"tokens/spacing.css"},{"name":"--radius-sm","value":"0.25rem","kind":"radius","definedIn":"tokens/spacing.css"},{"name":"--radius-md","value":"0.5rem","kind":"radius","definedIn":"tokens/spacing.css"},{"name":"--radius-lg","value":"0.75rem","kind":"radius","definedIn":"tokens/spacing.css"},{"name":"--radius-xl","value":"1rem","kind":"radius","definedIn":"tokens/spacing.css"},{"name":"--radius-2xl","value":"1.5rem","kind":"radius","definedIn":"tokens/spacing.css"},{"name":"--radius-pill","value":"50rem","kind":"radius","definedIn":"tokens/spacing.css"},{"name":"--radius-circle","value":"50%","kind":"radius","definedIn":"tokens/spacing.css"},{"name":"--shadow-xs","value":"0 2px 9px -5px rgba(0, 0, 0, 0.15)","kind":"shadow","definedIn":"tokens/spacing.css"},{"name":"--shadow","value":"0 0.3125rem 0.625rem 0 rgba(0, 0, 0, 0.12)","kind":"shadow","definedIn":"tokens/spacing.css"},{"name":"--shadow-lg","value":"0 8px 26px -4px rgba(20, 20, 20, 0.15), 0 8px 9px -5px rgba(20, 20, 20, 0.06)","kind":"shadow","definedIn":"tokens/spacing.css"},{"name":"--shadow-xl","value":"0 23px 45px -11px rgba(20, 20, 20, 0.25)","kind":"shadow","definedIn":"tokens/spacing.css"},{"name":"--shadow-btn","value":"0 4px 7px -1px rgba(0, 0, 0, 0.11), 0 2px 4px -1px rgba(0, 0, 0, 0.07)","kind":"shadow","definedIn":"tokens/spacing.css"},{"name":"--shadow-inset","value":"inset 0 1px 2px rgba(0, 0, 0, 0.075)","kind":"shadow","definedIn":"tokens/spacing.css"},{"name":"--ease-base","value":"all 0.2s ease-in-out","kind":"other","definedIn":"tokens/spacing.css","annotation":"other"},{"name":"--ease-soft","value":"all 0.25s ease","kind":"other","definedIn":"tokens/spacing.css","annotation":"other"},{"name":"--ease-btn","value":"all 0.15s ease-in","kind":"other","definedIn":"tokens/spacing.css","annotation":"other"},{"name":"--ease-bounce","value":"all 0.2s cubic-bezier(0.34, 1.61, 0.7, 1.3)","kind":"other","definedIn":"tokens/spacing.css","annotation":"other"},{"name":"--hover-lift","value":"scale(1.02)","kind":"other","definedIn":"tokens/spacing.css","annotation":"other"},{"name":"--border-width","value":"1px","kind":"spacing","definedIn":"tokens/spacing.css","annotation":"spacing"}],"themes":[{"selector":"[data-theme=\"dark\"]","label":"Dark"},{"selector":"[data-theme=\"light\"]","label":"Light"}],"fonts":[],"brandFonts":[{"family":"Open Sans","status":"ok","tokens":["--font-sans"],"path":"tokens/typography.css"}],"source":"spa"}